[
  {
    "id": 1,
    "jobId": 101,
    "studentId": 1,
    "companyName": "TechNova",
    "jobTitle": "Frontend Developer Intern",
    "status": "Under Review",
    "appliedAt": "2025-10-15T10:00:00Z"
  },
  {
    "id": 2,
    "jobId": 102,
    "studentId": 1,
    "companyName": "DataWorks",
    "jobTitle": "Data Analyst",
    "status": "Shortlisted",
    "appliedAt": "2025-10-20T14:30:00Z"
  },
  {
    "id": 3,
    "jobId": 103,
    "studentId": 1,
    "companyName": "CyberGrid",
    "jobTitle": "Security Intern",
    "status": "Rejected",
    "appliedAt": "2025-10-22T11:45:00Z"
  }
]
